pydstir/__init__.py
pydstir/colors.json
pydstir/main.py
pydstir/ops.py
pydstir-1.2.3.dist-info/METADATA
pydstir-1.2.3.dist-info/WHEEL
pydstir-1.2.3.dist-info/entry_points.txt
pydstir-1.2.3.dist-info/top_level.txt
pydstir-1.2.3.dist-info/RECORD
