Metadata-Version: 2.1
Name: pydstir
Version: 1.2.3
Summary: a module for pydstir tool from discord
Home-page: https://anarchydev.com
Author: Bernard Namou
Author-email: zalkoweb@anarchydev.com
Classifier: Programming Language :: Python :: 3
Classifier: License :: OSI Approved :: MIT License
Classifier: Operating System :: OS Independent
Requires-Dist: setuptools
Requires-Dist: columnar (>=1.3.1)
Requires-Dist: colorama
